README.md
setup.py
binance_transaction/__init__.py
binance_transaction/base.py
binance_transaction/bech32.py
binance_transaction/bnb_transaction.py
binance_transaction/crypto.py
binance_transaction/dex.py
binance_transaction/exceptions.py
binance_transaction/gov.py
binance_transaction/msg.py
binance_transaction/signature.py
binance_transaction/token.py
bnb_tx.egg-info/PKG-INFO
bnb_tx.egg-info/SOURCES.txt
bnb_tx.egg-info/dependency_links.txt
bnb_tx.egg-info/requires.txt
bnb_tx.egg-info/top_level.txt