Metadata-Version: 2.1
Name: bnb-tx
Version: 0.0.4
Summary: Binance Chain Transactions
Home-page: https://github.com/trusttoken/bnb-tx-python
Author: William Morriss
Author-email: wjmelements@gmail.com
License: UNKNOWN
Platform: UNKNOWN
Classifier: Programming Language :: Python :: 3
Classifier: License :: OSI Approved :: GNU Lesser General Public License v3 (LGPLv3)
Classifier: Operating System :: OS Independent
